{
  "users": [
    {
      "email": "prova@hotmail.it",
      "password": "$2a$10$VV9THof2iwUjFQdymXK08OpC87sG4.M054opU8fnQplh.x7nDGL8C",
      "name": "Lorenzo",
      "surname": "De Carolis",
      "id": 1
    },
    {
      "email": "davide@david.it",
      "password": "$2a$10$SNbPQMHskKBTSvcYnanahe6o57apbCVI2cPtBXV41KD7vM1Glf7Qm",
      "name": "Davide",
      "surname": "Alfonsi",
      "id": 2
    },
    {
      "email": "luca@david.it",
      "password": "$2a$10$2mSkGEHe2fyt3wpspmjDnezboc91eUnJZwpmCWpQSuBX4MYEuzmd6",
      "name": "Luca",
      "surname": "Alfonsi",
      "id": 3
    },
    {
      "email": "ilaria.cognata@gmail.com",
      "password": "$2a$10$mZOkhDjCQMEWiw1bGpaW1uqCjrP58vzLqNj5D0OlGJBOlCapPkzqq",
      "name": "ilaria",
      "surname": "cognata",
      "id": 4
    },
    {
      "email": "prova1@hotmail.it",
      "password": "$2a$10$2jWZ2C7SVi7XcbNLxh1emevdTUg1y6YfZSqP27qDRUT85p4j2ratu",
      "name": "Lorenzo",
      "surname": "Altomonte",
      "id": 3
    },
    {
      "email": "d@david.it",
      "password": "$2a$10$1PzAXbeUuREO/ZPb5vcgjue0CWxK21KVj4cQ8F5uyPy6eLwX5QxMi",
      "name": "luca",
      "surname": "luca",
      "avatar": "/assets/icon/1.png",
      "id": 5
    }
  ],
  "post": [
    {
      "title": "piove",
      "description": "cacca",
      "emoji": "tag_faces",
      "commenti": [
        "o",
        "cacca",
        "cacchetta"
      ],
      "date": {
        "mese": 11,
        "giorno": 13,
        "ora": 19,
        "minuti": 39
      },
      "user_id": 3,
      "id": 11
    },
    {
      "user_id": 4,
      "title": "piove",
      "description": "caccone",
      "emoji": "tag_faces",
      "commenti": [],
      "date": {
        "mese": 11,
        "giorno": 14,
        "ora": 11,
        "minuti": 9
      },
      "id": 12
    },
    {
      "title": "aaaaaaaa",
      "description": "È universalmente riconosciuto che un lettore che osserva il layout di una pagina viene distratto dal contenuto testuale se questo è leggibile. Lo scopo dell’utilizzo del Lorem Ipsum è che offre una normale distribuzione delle lettere (al contrario di quanto avviene se si utilizzano brevi frasi ripetute, ad esempio “testo qui”), apparendo come un normale blocco di testo leggibile. Molti software di impaginazione e di web design utilizzano Lorem Ipsum come testo modello. Molte versioni del testo sono state prodotte negli anni, a volte casualmente, a volte di proposito (ad esempio inserendo passaggi ironici).",
      "emoji": "Triste",
      "commenti": [
        "o"
      ],
      "date": {
        "mese": 11,
        "giorno": 14,
        "ora": 16,
        "minuti": 23
      },
      "user_id": 5,
      "id": 13
    },
    {
      "user_id": 5,
      "title": "Ciao",
      "description": "Tradotto dall'inglese-Il testo di riempimento è un testo che condivide alcune caratteristiche di un testo scritto reale, ma è casuale o generato in altro modo. Può essere utilizzato per visualizzare un campione di caratteri, generare testo per il test o per falsificare un filtro antispam di posta elettronica",
      "img": "/assets/images/1.jpg",
      "emoji": "Triste",
      "commenti": [],
      "date": {
        "mese": 11,
        "giorno": 14,
        "ora": 18,
        "minuti": 21
      },
      "id": 14
    }
  ],
  "favorites": [
    {
      "postId": 8,
      "userId": 1,
      "id": 1
    },
    {
      "postId": 8,
      "userId": 2,
      "id": 2
    }
  ]
}